README.md
setup.cfg
setup.py
pySGDabao/__init__.py
pySGDabao/deliveroo.py
pySGDabao/foodpanda.py
pySGDabao/honestbee.py
pySGDabao/utils.py
pySGDabao.egg-info/PKG-INFO
pySGDabao.egg-info/SOURCES.txt
pySGDabao.egg-info/dependency_links.txt
pySGDabao.egg-info/requires.txt
pySGDabao.egg-info/top_level.txt