Metadata-Version: 2.1
Name: pySGDabao
Version: 1.0.1
Summary: A library for your Singapore food delivery needs
Home-page: https://github.com/rizemon/pySGDabao
Author: rizemon
Author-email: tan.jia.le.98@gmail.com
License: Apache License 2.0
Download-URL: https://github.com/rizemon/pySGDabao/archive/v1.0.1.tar.gz
Keywords: Foodpanda,Deliveroo,Honestbee
Platform: UNKNOWN
Classifier: Development Status :: 4 - Beta
Classifier: Intended Audience :: Developers
Classifier: Topic :: Software Development :: Build Tools
Classifier: License :: OSI Approved :: Apache Software License
Classifier: Programming Language :: Python :: 3
Classifier: Programming Language :: Python :: 3.4
Classifier: Programming Language :: Python :: 3.5
Classifier: Programming Language :: Python :: 3.6
Classifier: Programming Language :: Python :: 3.7
Classifier: Programming Language :: Python :: 3.8
